{
  "schedule": [
    {
      "adjusted_load_kwh": 0.36,
      "adjusted_pv_kwh": 0,
      "battery_charge_kw": 0,
      "battery_discharge_kw": 0,
      "charge_kw": 0,
      "classification": "hold",
      "end_time": "2025-11-04T00:15:00+01:00",
      "export_kwh": 0,
      "export_price_sek_kwh": 0.04,
      "export_revenue": 0,
      "import_price_sek_kwh": 0.9,
      "is_cheap": true,
      "load_forecast_kwh": 0.34,
      "priority": "low",
      "projected_battery_cost": 0.2,
      "projected_soc_kwh": 30.94,
      "projected_soc_percent": 91,
      "pv_forecast_kwh": 0,
      "reason": "no_action_needed",
      "slot_number": 1,
      "soc_target_percent": 91,
      "start_time": "2025-11-04T00:00:00+01:00",
      "water_from_battery_kwh": 0,
      "water_from_grid_kwh": 0,
      "water_from_pv_kwh": 0,
      "water_heating_kw": 0
    },
    {
      "adjusted_load_kwh": 0.45,
      "adjusted_pv_kwh": 0,
      "battery_charge_kw": 0,
      "battery_discharge_kw": 0,
      "charge_kw": 0,
      "classification": "hold",
      "end_time": "2025-11-04T00:30:00+01:00",
      "export_kwh": 0,
      "export_price_sek_kwh": 0.05,
      "export_revenue": 0,
      "import_price_sek_kwh": 0.91,
      "is_cheap": true,
      "load_forecast_kwh": 0.43,
      "priority": "low",
      "projected_battery_cost": 0.2,
      "projected_soc_kwh": 30.94,
      "projected_soc_percent": 91,
      "pv_forecast_kwh": 0,
      "reason": "no_action_needed",
      "slot_number": 2,
      "soc_target_percent": 91,
      "start_time": "2025-11-04T00:15:00+01:00",
      "water_from_battery_kwh": 0,
      "water_from_grid_kwh": 0,
      "water_from_pv_kwh": 0,
      "water_heating_kw": 0
    },
    {
      "adjusted_load_kwh": 0.48,
      "adjusted_pv_kwh": 0,
      "battery_charge_kw": 0,
      "battery_discharge_kw": 0,
      "charge_kw": 0,
      "classification": "hold",
      "end_time": "2025-11-04T00:45:00+01:00",
      "export_kwh": 0,
      "export_price_sek_kwh": 0.03,
      "export_revenue": 0,
      "import_price_sek_kwh": 0.9,
      "is_cheap": true,
      "load_forecast_kwh": 0.45,
      "priority": "low",
      "projected_battery_cost": 0.2,
      "projected_soc_kwh": 30.94,
      "projected_soc_percent": 91,
      "pv_forecast_kwh": 0,
      "reason": "no_action_needed",
      "slot_number": 3,
      "soc_target_percent": 91,
      "start_time": "2025-11-04T00:30:00+01:00",
      "water_from_battery_kwh": 0,
      "water_from_grid_kwh": 0,
      "water_from_pv_kwh": 0,
      "water_heating_kw": 0
    },
    {
      "adjusted_load_kwh": 0.42,
      "adjusted_pv_kwh": 0,
      "battery_charge_kw": 0,
      "battery_discharge_kw": 0,
      "charge_kw": 0,
      "classification": "hold",
      "end_time": "2025-11-04T01:00:00+01:00",
      "export_kwh": 0,
      "export_price_sek_kwh": 0.03,
      "export_revenue": 0,
      "import_price_sek_kwh": 0.9,
      "is_cheap": true,
      "load_forecast_kwh": 0.4,
      "priority": "low",
      "projected_battery_cost": 0.2,
      "projected_soc_kwh": 30.94,
      "projected_soc_percent": 91,
      "pv_forecast_kwh": 0,
      "reason": "no_action_needed",
      "slot_number": 4,
      "soc_target_percent": 91,
      "start_time": "2025-11-04T00:45:00+01:00",
      "water_from_battery_kwh": 0,
      "water_from_grid_kwh": 0,
      "water_from_pv_kwh": 0,
      "water_heating_kw": 0
    },
    {
      "adjusted_load_kwh": 0.29,
      "adjusted_pv_kwh": 0,
      "battery_charge_kw": 0,
      "battery_discharge_kw": 0,
      "charge_kw": 0,
      "classification": "hold",
      "end_time": "2025-11-04T01:15:00+01:00",
      "export_kwh": 0,
      "export_price_sek_kwh": 0.02,
      "export_revenue": 0,
      "import_price_sek_kwh": 0.88,
      "is_cheap": true,
      "load_forecast_kwh": 0.28,
      "priority": "low",
      "projected_battery_cost": 0.2,
      "projected_soc_kwh": 30.94,
      "projected_soc_percent": 91,
      "pv_forecast_kwh": 0,
      "reason": "no_action_needed",
      "slot_number": 5,
      "soc_target_percent": 91,
      "start_time": "2025-11-04T01:00:00+01:00",
      "water_from_battery_kwh": 0,
      "water_from_grid_kwh": 0,
      "water_from_pv_kwh": 0,
      "water_heating_kw": 0
    },
    {
      "adjusted_load_kwh": 0.16,
      "adjusted_pv_kwh": 0,
      "battery_charge_kw": 0,
      "battery_discharge_kw": 0,
      "charge_kw": 0,
      "classification": "hold",
      "end_time": "2025-11-04T01:30:00+01:00",
      "export_kwh": 0,
      "export_price_sek_kwh": 0.02,
      "export_revenue": 0,
      "import_price_sek_kwh": 0.88,
      "is_cheap": true,
      "load_forecast_kwh": 0.15,
      "priority": "low",
      "projected_battery_cost": 0.2,
      "projected_soc_kwh": 30.94,
      "projected_soc_percent": 91,
      "pv_forecast_kwh": 0,
      "reason": "no_action_needed",
      "slot_number": 6,
      "soc_target_percent": 91,
      "start_time": "2025-11-04T01:15:00+01:00",
      "water_from_battery_kwh": 0,
      "water_from_grid_kwh": 0,
      "water_from_pv_kwh": 0,
      "water_heating_kw": 0
    },
    {
      "adjusted_load_kwh": 0.17,
      "adjusted_pv_kwh": 0,
      "battery_charge_kw": 0,
      "battery_discharge_kw": 0,
      "charge_kw": 0,
      "classification": "hold",
      "end_time": "2025-11-04T01:45:00+01:00",
      "export_kwh": 0,
      "export_price_sek_kwh": 0.02,
      "export_revenue": 0,
      "import_price_sek_kwh": 0.88,
      "is_cheap": true,
      "load_forecast_kwh": 0.16,
      "priority": "low",
      "projected_battery_cost": 0.2,
      "projected_soc_kwh": 30.94,
      "projected_soc_percent": 91,
      "pv_forecast_kwh": 0,
      "reason": "no_action_needed",
      "slot_number": 7,
      "soc_target_percent": 91,
      "start_time": "2025-11-04T01:30:00+01:00",
      "water_from_battery_kwh": 0,
      "water_from_grid_kwh": 0,
      "water_from_pv_kwh": 0,
      "water_heating_kw": 0
    },
    {
      "adjusted_load_kwh": 0.21,
      "adjusted_pv_kwh": 0,
      "battery_charge_kw": 0,
      "battery_discharge_kw": 0,
      "charge_kw": 0,
      "classification": "hold",
      "end_time": "2025-11-04T02:00:00+01:00",
      "export_kwh": 0,
      "export_price_sek_kwh": 0.02,
      "export_revenue": 0,
      "import_price_sek_kwh": 0.88,
      "is_cheap": true,
      "load_forecast_kwh": 0.2,
      "priority": "low",
      "projected_battery_cost": 0.2,
      "projected_soc_kwh": 30.94,
      "projected_soc_percent": 91,
      "pv_forecast_kwh": 0,
      "reason": "no_action_needed",
      "slot_number": 8,
      "soc_target_percent": 91,
      "start_time": "2025-11-04T01:45:00+01:00",
      "water_from_battery_kwh": 0,
      "water_from_grid_kwh": 0,
      "water_from_pv_kwh": 0,
      "water_heating_kw": 0
    },
    {
      "adjusted_load_kwh": 0.2,
      "adjusted_pv_kwh": 0,
      "battery_charge_kw": 0,
      "battery_discharge_kw": 0,
      "charge_kw": 0,
      "classification": "hold",
      "end_time": "2025-11-04T02:15:00+01:00",
      "export_kwh": 0,
      "export_price_sek_kwh": 0.02,
      "export_revenue": 0,
      "import_price_sek_kwh": 0.88,
      "is_cheap": true,
      "load_forecast_kwh": 0.19,
      "priority": "low",
      "projected_battery_cost": 0.2,
      "projected_soc_kwh": 30.94,
      "projected_soc_percent": 91,
      "pv_forecast_kwh": 0,
      "reason": "no_action_needed",
      "slot_number": 9,
      "soc_target_percent": 91,
      "start_time": "2025-11-04T02:00:00+01:00",
      "water_from_battery_kwh": 0,
      "water_from_grid_kwh": 0,
      "water_from_pv_kwh": 0,
      "water_heating_kw": 0
    },
    {
      "adjusted_load_kwh": 0.19,
      "adjusted_pv_kwh": 0,
      "battery_charge_kw": 0,
      "battery_discharge_kw": 0,
      "charge_kw": 0,
      "classification": "hold",
      "end_time": "2025-11-04T02:30:00+01:00",
      "export_kwh": 0,
      "export_price_sek_kwh": 0.02,
      "export_revenue": 0,
      "import_price_sek_kwh": 0.88,
      "is_cheap": true,
      "load_forecast_kwh": 0.18,
      "priority": "low",
      "projected_battery_cost": 0.2,
      "projected_soc_kwh": 30.94,
      "projected_soc_percent": 91,
      "pv_forecast_kwh": 0,
      "reason": "no_action_needed",
      "slot_number": 10,
      "soc_target_percent": 91,
      "start_time": "2025-11-04T02:15:00+01:00",
      "water_from_battery_kwh": 0,
      "water_from_grid_kwh": 0,
      "water_from_pv_kwh": 0,
      "water_heating_kw": 0
    },
    {
      "adjusted_load_kwh": 0.17,
      "adjusted_pv_kwh": 0,
      "battery_charge_kw": 0,
      "battery_discharge_kw": 0,
      "charge_kw": 0,
      "classification": "hold",
      "end_time": "2025-11-04T02:45:00+01:00",
      "export_kwh": 0,
      "export_price_sek_kwh": 0.01,
      "export_revenue": 0,
      "import_price_sek_kwh": 0.87,
      "is_cheap": true,
      "load_forecast_kwh": 0.16,
      "priority": "low",
      "projected_battery_cost": 0.2,
      "projected_soc_kwh": 30.94,
      "projected_soc_percent": 91,
      "pv_forecast_kwh": 0,
      "reason": "no_action_needed",
      "slot_number": 11,
      "soc_target_percent": 91,
      "start_time": "2025-11-04T02:30:00+01:00",
      "water_from_battery_kwh": 0,
      "water_from_grid_kwh": 0,
      "water_from_pv_kwh": 0,
      "water_heating_kw": 0
    },
    {
      "adjusted_load_kwh": 0.18,
      "adjusted_pv_kwh": 0,
      "battery_charge_kw": 0,
      "battery_discharge_kw": 0,
      "charge_kw": 0,
      "classification": "hold",
      "end_time": "2025-11-04T03:00:00+01:00",
      "export_kwh": 0,
      "export_price_sek_kwh": 0.01,
      "export_revenue": 0,
      "import_price_sek_kwh": 0.87,
      "is_cheap": true,
      "load_forecast_kwh": 0.17,
      "priority": "low",
      "projected_battery_cost": 0.2,
      "projected_soc_kwh": 30.94,
      "projected_soc_percent": 91,
      "pv_forecast_kwh": 0,
      "reason": "no_action_needed",
      "slot_number": 12,
      "soc_target_percent": 91,
      "start_time": "2025-11-04T02:45:00+01:00",
      "water_from_battery_kwh": 0,
      "water_from_grid_kwh": 0,
      "water_from_pv_kwh": 0,
      "water_heating_kw": 0
    },
    {
      "adjusted_load_kwh": 0.18,
      "adjusted_pv_kwh": 0,
      "battery_charge_kw": 0,
      "battery_discharge_kw": 0,
      "charge_kw": 0,
      "classification": "hold",
      "end_time": "2025-11-04T03:15:00+01:00",
      "export_kwh": 0,
      "export_price_sek_kwh": 0.02,
      "export_revenue": 0,
      "import_price_sek_kwh": 0.88,
      "is_cheap": true,
      "load_forecast_kwh": 0.17,
      "priority": "low",
      "projected_battery_cost": 0.2,
      "projected_soc_kwh": 30.94,
      "projected_soc_percent": 91,
      "pv_forecast_kwh": 0,
      "reason": "no_action_needed",
      "slot_number": 13,
      "soc_target_percent": 91,
      "start_time": "2025-11-04T03:00:00+01:00",
      "water_from_battery_kwh": 0,
      "water_from_grid_kwh": 0,
      "water_from_pv_kwh": 0,
      "water_heating_kw": 0
    },
    {
      "adjusted_load_kwh": 0.17,
      "adjusted_pv_kwh": 0,
      "battery_charge_kw": 0,
      "battery_discharge_kw": 0,
      "charge_kw": 0,
      "classification": "hold",
      "end_time": "2025-11-04T03:30:00+01:00",
      "export_kwh": 0,
      "export_price_sek_kwh": 0.02,
      "export_revenue": 0,
      "import_price_sek_kwh": 0.88,
      "is_cheap": true,
      "load_forecast_kwh": 0.17,
      "priority": "low",
      "projected_battery_cost": 0.2,
      "projected_soc_kwh": 30.94,
      "projected_soc_percent": 91,
      "pv_forecast_kwh": 0,
      "reason": "no_action_needed",
      "slot_number": 14,
      "soc_target_percent": 91,
      "start_time": "2025-11-04T03:15:00+01:00",
      "water_from_battery_kwh": 0,
      "water_from_grid_kwh": 0,
      "water_from_pv_kwh": 0,
      "water_heating_kw": 0
    },
    {
      "adjusted_load_kwh": 0.18,
      "adjusted_pv_kwh": 0,
      "battery_charge_kw": 0,
      "battery_discharge_kw": 0,
      "charge_kw": 0,
      "classification": "hold",
      "end_time": "2025-11-04T03:45:00+01:00",
      "export_kwh": 0,
      "export_price_sek_kwh": 0.02,
      "export_revenue": 0,
      "import_price_sek_kwh": 0.88,
      "is_cheap": true,
      "load_forecast_kwh": 0.17,
      "priority": "low",
      "projected_battery_cost": 0.2,
      "projected_soc_kwh": 30.94,
      "projected_soc_percent": 91,
      "pv_forecast_kwh": 0,
      "reason": "no_action_needed",
      "slot_number": 15,
      "soc_target_percent": 91,
      "start_time": "2025-11-04T03:30:00+01:00",
      "water_from_battery_kwh": 0,
      "water_from_grid_kwh": 0,
      "water_from_pv_kwh": 0,
      "water_heating_kw": 0
    },
    {
      "adjusted_load_kwh": 0.16,
      "adjusted_pv_kwh": 0,
      "battery_charge_kw": 0,
      "battery_discharge_kw": 0,
      "charge_kw": 0,
      "classification": "hold",
      "end_time": "2025-11-04T04:00:00+01:00",
      "export_kwh": 0,
      "export_price_sek_kwh": 0.01,
      "export_revenue": 0,
      "import_price_sek_kwh": 0.87,
      "is_cheap": true,
      "load_forecast_kwh": 0.15,
      "priority": "low",
      "projected_battery_cost": 0.2,
      "projected_soc_kwh": 30.94,
      "projected_soc_percent": 91,
      "pv_forecast_kwh": 0,
      "reason": "no_action_needed",
      "slot_number": 16,
      "soc_target_percent": 91,
      "start_time": "2025-11-04T03:45:00+01:00",
      "water_from_battery_kwh": 0,
      "water_from_grid_kwh": 0,
      "water_from_pv_kwh": 0,
      "water_heating_kw": 0
    },
    {
      "adjusted_load_kwh": 0.18,
      "adjusted_pv_kwh": 0,
      "battery_charge_kw": 0,
      "battery_discharge_kw": 0,
      "charge_kw": 0,
      "classification": "hold",
      "end_time": "2025-11-04T04:15:00+01:00",
      "export_kwh": 0,
      "export_price_sek_kwh": 0.02,
      "export_revenue": 0,
      "import_price_sek_kwh": 0.88,
      "is_cheap": true,
      "load_forecast_kwh": 0.17,
      "priority": "low",
      "projected_battery_cost": 0.2,
      "projected_soc_kwh": 30.94,
      "projected_soc_percent": 91,
      "pv_forecast_kwh": 0,
      "reason": "no_action_needed",
      "slot_number": 17,
      "soc_target_percent": 91,
      "start_time": "2025-11-04T04:00:00+01:00",
      "water_from_battery_kwh": 0,
      "water_from_grid_kwh": 0,
      "water_from_pv_kwh": 0,
      "water_heating_kw": 0
    },
    {
      "adjusted_load_kwh": 0.19,
      "adjusted_pv_kwh": 0,
      "battery_charge_kw": 0,
      "battery_discharge_kw": 0,
      "charge_kw": 0,
      "classification": "hold",
      "end_time": "2025-11-04T04:30:00+01:00",
      "export_kwh": 0,
      "export_price_sek_kwh": 0.02,
      "export_revenue": 0,
      "import_price_sek_kwh": 0.88,
      "is_cheap": true,
      "load_forecast_kwh": 0.18,
      "priority": "low",
      "projected_battery_cost": 0.2,
      "projected_soc_kwh": 30.94,
      "projected_soc_percent": 91,
      "pv_forecast_kwh": 0,
      "reason": "no_action_needed",
      "slot_number": 18,
      "soc_target_percent": 91,
      "start_time": "2025-11-04T04:15:00+01:00",
      "water_from_battery_kwh": 0,
      "water_from_grid_kwh": 0,
      "water_from_pv_kwh": 0,
      "water_heating_kw": 0
    },
    {
      "adjusted_load_kwh": 0.19,
      "adjusted_pv_kwh": 0,
      "battery_charge_kw": 0,
      "battery_discharge_kw": 0,
      "charge_kw": 0,
      "classification": "hold",
      "end_time": "2025-11-04T04:45:00+01:00",
      "export_kwh": 0,
      "export_price_sek_kwh": 0.01,
      "export_revenue": 0,
      "import_price_sek_kwh": 0.87,
      "is_cheap": true,
      "load_forecast_kwh": 0.18,
      "priority": "low",
      "projected_battery_cost": 0.2,
      "projected_soc_kwh": 30.94,
      "projected_soc_percent": 91,
      "pv_forecast_kwh": 0,
      "reason": "no_action_needed",
      "slot_number": 19,
      "soc_target_percent": 91,
      "start_time": "2025-11-04T04:30:00+01:00",
      "water_from_battery_kwh": 0,
      "water_from_grid_kwh": 0,
      "water_from_pv_kwh": 0,
      "water_heating_kw": 0
    },
    {
      "adjusted_load_kwh": 0.16,
      "adjusted_pv_kwh": 0,
      "battery_charge_kw": 0,
      "battery_discharge_kw": 0,
      "charge_kw": 0,
      "classification": "hold",
      "end_time": "2025-11-04T05:00:00+01:00",
      "export_kwh": 0,
      "export_price_sek_kwh": 0.02,
      "export_revenue": 0,
      "import_price_sek_kwh": 0.88,
      "is_cheap": true,
      "load_forecast_kwh": 0.15,
      "priority": "low",
      "projected_battery_cost": 0.2,
      "projected_soc_kwh": 30.94,
      "projected_soc_percent": 91,
      "pv_forecast_kwh": 0,
      "reason": "no_action_needed",
      "slot_number": 20,
      "soc_target_percent": 91,
      "start_time": "2025-11-04T04:45:00+01:00",
      "water_from_battery_kwh": 0,
      "water_from_grid_kwh": 0,
      "water_from_pv_kwh": 0,
      "water_heating_kw": 0
    },
    {
      "adjusted_load_kwh": 0.18,
      "adjusted_pv_kwh": 0,
      "battery_charge_kw": 0,
      "battery_discharge_kw": 0,
      "charge_kw": 0,
      "classification": "hold",
      "end_time": "2025-11-04T05:15:00+01:00",
      "export_kwh": 0,
      "export_price_sek_kwh": 0.01,
      "export_revenue": 0,
      "import_price_sek_kwh": 0.87,
      "is_cheap": true,
      "load_forecast_kwh": 0.17,
      "priority": "low",
      "projected_battery_cost": 0.2,
      "projected_soc_kwh": 30.94,
      "projected_soc_percent": 91,
      "pv_forecast_kwh": 0,
      "reason": "no_action_needed",
      "slot_number": 21,
      "soc_target_percent": 91,
      "start_time": "2025-11-04T05:00:00+01:00",
      "water_from_battery_kwh": 0,
      "water_from_grid_kwh": 0,
      "water_from_pv_kwh": 0,
      "water_heating_kw": 0
    },
    {
      "adjusted_load_kwh": 0.19,
      "adjusted_pv_kwh": 0,
      "battery_charge_kw": 0,
      "battery_discharge_kw": 0,
      "charge_kw": 0,
      "classification": "hold",
      "end_time": "2025-11-04T05:30:00+01:00",
      "export_kwh": 0,
      "export_price_sek_kwh": 0.02,
      "export_revenue": 0,
      "import_price_sek_kwh": 0.88,
      "is_cheap": true,
      "load_forecast_kwh": 0.18,
      "priority": "low",
      "projected_battery_cost": 0.2,
      "projected_soc_kwh": 30.94,
      "projected_soc_percent": 91,
      "pv_forecast_kwh": 0,
      "reason": "no_action_needed",
      "slot_number": 22,
      "soc_target_percent": 91,
      "start_time": "2025-11-04T05:15:00+01:00",
      "water_from_battery_kwh": 0,
      "water_from_grid_kwh": 0,
      "water_from_pv_kwh": 0,
      "water_heating_kw": 0
    },
    {
      "adjusted_load_kwh": 0.16,
      "adjusted_pv_kwh": 0,
      "battery_charge_kw": 0,
      "battery_discharge_kw": 0,
      "charge_kw": 0,
      "classification": "hold",
      "end_time": "2025-11-04T05:45:00+01:00",
      "export_kwh": 0,
      "export_price_sek_kwh": 0.03,
      "export_revenue": 0,
      "import_price_sek_kwh": 0.89,
      "is_cheap": true,
      "load_forecast_kwh": 0.16,
      "priority": "low",
      "projected_battery_cost": 0.2,
      "projected_soc_kwh": 30.94,
      "projected_soc_percent": 91,
      "pv_forecast_kwh": 0,
      "reason": "no_action_needed",
      "slot_number": 23,
      "soc_target_percent": 91,
      "start_time": "2025-11-04T05:30:00+01:00",
      "water_from_battery_kwh": 0,
      "water_from_grid_kwh": 0,
      "water_from_pv_kwh": 0,
      "water_heating_kw": 0
    },
    {
      "adjusted_load_kwh": 0.2,
      "adjusted_pv_kwh": 0,
      "battery_charge_kw": 0,
      "battery_discharge_kw": 0,
      "charge_kw": 0,
      "classification": "hold",
      "end_time": "2025-11-04T06:00:00+01:00",
      "export_kwh": 0,
      "export_price_sek_kwh": 0.03,
      "export_revenue": 0,
      "import_price_sek_kwh": 0.9,
      "is_cheap": true,
      "load_forecast_kwh": 0.19,
      "priority": "low",
      "projected_battery_cost": 0.2,
      "projected_soc_kwh": 30.94,
      "projected_soc_percent": 91,
      "pv_forecast_kwh": 0,
      "reason": "no_action_needed",
      "slot_number": 24,
      "soc_target_percent": 91,
      "start_time": "2025-11-04T05:45:00+01:00",
      "water_from_battery_kwh": 0,
      "water_from_grid_kwh": 0,
      "water_from_pv_kwh": 0,
      "water_heating_kw": 0
    },
    {
      "adjusted_load_kwh": 0.26,
      "adjusted_pv_kwh": 0,
      "battery_charge_kw": 0,
      "battery_discharge_kw": 0,
      "charge_kw": 0,
      "classification": "hold",
      "end_time": "2025-11-04T06:15:00+01:00",
      "export_kwh": 0,
      "export_price_sek_kwh": 0,
      "export_revenue": 0,
      "import_price_sek_kwh": 0.86,
      "is_cheap": true,
      "load_forecast_kwh": 0.25,
      "priority": "low",
      "projected_battery_cost": 0.2,
      "projected_soc_kwh": 30.94,
      "projected_soc_percent": 91,
      "pv_forecast_kwh": 0,
      "reason": "no_action_needed",
      "slot_number": 25,
      "soc_target_percent": 91,
      "start_time": "2025-11-04T06:00:00+01:00",
      "water_from_battery_kwh": 0,
      "water_from_grid_kwh": 0,
      "water_from_pv_kwh": 0,
      "water_heating_kw": 0
    },
    {
      "adjusted_load_kwh": 0.24,
      "adjusted_pv_kwh": 0,
      "battery_charge_kw": 0,
      "battery_discharge_kw": 0,
      "charge_kw": 0,
      "classification": "hold",
      "end_time": "2025-11-04T06:30:00+01:00",
      "export_kwh": 0,
      "export_price_sek_kwh": 0.02,
      "export_revenue": 0,
      "import_price_sek_kwh": 0.89,
      "is_cheap": true,
      "load_forecast_kwh": 0.22,
      "priority": "low",
      "projected_battery_cost": 0.2,
      "projected_soc_kwh": 30.94,
      "projected_soc_percent": 91,
      "pv_forecast_kwh": 0,
      "reason": "no_action_needed",
      "slot_number": 26,
      "soc_target_percent": 91,
      "start_time": "2025-11-04T06:15:00+01:00",
      "water_from_battery_kwh": 0,
      "water_from_grid_kwh": 0,
      "water_from_pv_kwh": 0,
      "water_heating_kw": 0
    },
    {
      "adjusted_load_kwh": 0.26,
      "adjusted_pv_kwh": 0,
      "battery_charge_kw": 0,
      "battery_discharge_kw": 0,
      "charge_kw": 0,
      "classification": "hold",
      "end_time": "2025-11-04T06:45:00+01:00",
      "export_kwh": 0,
      "export_price_sek_kwh": 0.03,
      "export_revenue": 0,
      "import_price_sek_kwh": 0.89,
      "is_cheap": true,
      "load_forecast_kwh": 0.25,
      "priority": "low",
      "projected_battery_cost": 0.2,
      "projected_soc_kwh": 30.94,
      "projected_soc_percent": 91,
      "pv_forecast_kwh": 0,
      "reason": "no_action_needed",
      "slot_number": 27,
      "soc_target_percent": 91,
      "start_time": "2025-11-04T06:30:00+01:00",
      "water_from_battery_kwh": 0,
      "water_from_grid_kwh": 0,
      "water_from_pv_kwh": 0,
      "water_heating_kw": 0
    },
    {
      "adjusted_load_kwh": 0.28,
      "adjusted_pv_kwh": 0,
      "battery_charge_kw": 0,
      "battery_discharge_kw": 0,
      "charge_kw": 0,
      "classification": "hold",
      "end_time": "2025-11-04T07:00:00+01:00",
      "export_kwh": 0,
      "export_price_sek_kwh": 0.03,
      "export_revenue": 0,
      "import_price_sek_kwh": 0.89,
      "is_cheap": true,
      "load_forecast_kwh": 0.27,
      "priority": "low",
      "projected_battery_cost": 0.2,
      "projected_soc_kwh": 30.94,
      "projected_soc_percent": 91,
      "pv_forecast_kwh": 0,
      "reason": "no_action_needed",
      "slot_number": 28,
      "soc_target_percent": 91,
      "start_time": "2025-11-04T06:45:00+01:00",
      "water_from_battery_kwh": 0,
      "water_from_grid_kwh": 0,
      "water_from_pv_kwh": 0,
      "water_heating_kw": 0
    },
    {
      "adjusted_load_kwh": 0.31,
      "adjusted_pv_kwh": 0,
      "battery_charge_kw": 0,
      "battery_discharge_kw": 1.23,
      "charge_kw": 0,
      "classification": "discharge",
      "end_time": "2025-11-04T07:15:00+01:00",
      "export_kwh": 0,
      "export_price_sek_kwh": 0.3,
      "export_revenue": 0,
      "import_price_sek_kwh": 1.23,
      "is_cheap": false,
      "load_forecast_kwh": 0.29,
      "priority": "high",
      "projected_battery_cost": 0.2,
      "projected_soc_kwh": 30.62,
      "projected_soc_percent": 90.07,
      "pv_forecast_kwh": 0,
      "reason": "expensive_grid_power",
      "slot_number": 29,
      "soc_target_percent": 15,
      "start_time": "2025-11-04T07:00:00+01:00",
      "water_from_battery_kwh": 0,
      "water_from_grid_kwh": 0,
      "water_from_pv_kwh": 0,
      "water_heating_kw": 0
    },
    {
      "adjusted_load_kwh": 0.35,
      "adjusted_pv_kwh": 0,
      "battery_charge_kw": 0,
      "battery_discharge_kw": 1.4,
      "charge_kw": 0,
      "classification": "discharge",
      "end_time": "2025-11-04T07:30:00+01:00",
      "export_kwh": 0,
      "export_price_sek_kwh": 0.32,
      "export_revenue": 0,
      "import_price_sek_kwh": 1.26,
      "is_cheap": false,
      "load_forecast_kwh": 0.33,
      "priority": "high",
      "projected_battery_cost": 0.2,
      "projected_soc_kwh": 30.26,
      "projected_soc_percent": 89.01,
      "pv_forecast_kwh": 0,
      "reason": "expensive_grid_power",
      "slot_number": 30,
      "soc_target_percent": 15,
      "start_time": "2025-11-04T07:15:00+01:00",
      "water_from_battery_kwh": 0,
      "water_from_grid_kwh": 0,
      "water_from_pv_kwh": 0,
      "water_heating_kw": 0
    },
    {
      "adjusted_load_kwh": 0.37,
      "adjusted_pv_kwh": 0,
      "battery_charge_kw": 0,
      "battery_discharge_kw": 1.47,
      "charge_kw": 0,
      "classification": "discharge",
      "end_time": "2025-11-04T07:45:00+01:00",
      "export_kwh": 0,
      "export_price_sek_kwh": 0.33,
      "export_revenue": 0,
      "import_price_sek_kwh": 1.27,
      "is_cheap": false,
      "load_forecast_kwh": 0.35,
      "priority": "high",
      "projected_battery_cost": 0.2,
      "projected_soc_kwh": 29.89,
      "projected_soc_percent": 87.9,
      "pv_forecast_kwh": 0,
      "reason": "expensive_grid_power",
      "slot_number": 31,
      "soc_target_percent": 15,
      "start_time": "2025-11-04T07:30:00+01:00",
      "water_from_battery_kwh": 0,
      "water_from_grid_kwh": 0,
      "water_from_pv_kwh": 0,
      "water_heating_kw": 0
    },
    {
      "adjusted_load_kwh": 0.36,
      "adjusted_pv_kwh": 0,
      "battery_charge_kw": 0,
      "battery_discharge_kw": 1.42,
      "charge_kw": 0,
      "classification": "discharge",
      "end_time": "2025-11-04T08:00:00+01:00",
      "export_kwh": 0,
      "export_price_sek_kwh": 0.21,
      "export_revenue": 0,
      "import_price_sek_kwh": 1.12,
      "is_cheap": false,
      "load_forecast_kwh": 0.34,
      "priority": "high",
      "projected_battery_cost": 0.2,
      "projected_soc_kwh": 29.52,
      "projected_soc_percent": 86.84,
      "pv_forecast_kwh": 0,
      "reason": "expensive_grid_power",
      "slot_number": 32,
      "soc_target_percent": 15,
      "start_time": "2025-11-04T07:45:00+01:00",
      "water_from_battery_kwh": 0,
      "water_from_grid_kwh": 0,
      "water_from_pv_kwh": 0,
      "water_heating_kw": 0
    },
    {
      "adjusted_load_kwh": 0.32,
      "adjusted_pv_kwh": 0.01,
      "battery_charge_kw": 0,
      "battery_discharge_kw": 0,
      "charge_kw": 0,
      "classification": "hold",
      "end_time": "2025-11-04T08:15:00+01:00",
      "export_kwh": 0,
      "export_price_sek_kwh": 0.14,
      "export_revenue": 0,
      "import_price_sek_kwh": 1.03,
      "is_cheap": true,
      "load_forecast_kwh": 0.3,
      "priority": "low",
      "projected_battery_cost": 0.2,
      "projected_soc_kwh": 29.52,
      "projected_soc_percent": 86.84,
      "pv_forecast_kwh": 0.01,
      "reason": "no_action_needed",
      "slot_number": 33,
      "soc_target_percent": 86.84,
      "start_time": "2025-11-04T08:00:00+01:00",
      "water_from_battery_kwh": 0,
      "water_from_grid_kwh": 0,
      "water_from_pv_kwh": 0,
      "water_heating_kw": 0
    },
    {
      "adjusted_load_kwh": 0.3,
      "adjusted_pv_kwh": 0.01,
      "battery_charge_kw": 0,
      "battery_discharge_kw": 0,
      "charge_kw": 0,
      "classification": "hold",
      "end_time": "2025-11-04T08:30:00+01:00",
      "export_kwh": 0,
      "export_price_sek_kwh": 0.14,
      "export_revenue": 0,
      "import_price_sek_kwh": 1.03,
      "is_cheap": true,
      "load_forecast_kwh": 0.29,
      "priority": "low",
      "projected_battery_cost": 0.2,
      "projected_soc_kwh": 29.52,
      "projected_soc_percent": 86.84,
      "pv_forecast_kwh": 0.01,
      "reason": "no_action_needed",
      "slot_number": 34,
      "soc_target_percent": 86.84,
      "start_time": "2025-11-04T08:15:00+01:00",
      "water_from_battery_kwh": 0,
      "water_from_grid_kwh": 0,
      "water_from_pv_kwh": 0,
      "water_heating_kw": 0
    },
    {
      "adjusted_load_kwh": 0.23,
      "adjusted_pv_kwh": 0.01,
      "battery_charge_kw": 0,
      "battery_discharge_kw": 0,
      "charge_kw": 0,
      "classification": "hold",
      "end_time": "2025-11-04T08:45:00+01:00",
      "export_kwh": 0,
      "export_price_sek_kwh": 0.13,
      "export_revenue": 0,
      "import_price_sek_kwh": 1.02,
      "is_cheap": true,
      "load_forecast_kwh": 0.22,
      "priority": "low",
      "projected_battery_cost": 0.2,
      "projected_soc_kwh": 29.52,
      "projected_soc_percent": 86.84,
      "pv_forecast_kwh": 0.01,
      "reason": "no_action_needed",
      "slot_number": 35,
      "soc_target_percent": 86.84,
      "start_time": "2025-11-04T08:30:00+01:00",
      "water_from_battery_kwh": 0,
      "water_from_grid_kwh": 0,
      "water_from_pv_kwh": 0,
      "water_heating_kw": 0
    },
    {
      "adjusted_load_kwh": 0.31,
      "adjusted_pv_kwh": 0.02,
      "battery_charge_kw": 0,
      "battery_discharge_kw": 0,
      "charge_kw": 0,
      "classification": "hold",
      "end_time": "2025-11-04T09:00:00+01:00",
      "export_kwh": 0,
      "export_price_sek_kwh": 0.1,
      "export_revenue": 0,
      "import_price_sek_kwh": 0.98,
      "is_cheap": true,
      "load_forecast_kwh": 0.29,
      "priority": "low",
      "projected_battery_cost": 0.2,
      "projected_soc_kwh": 29.52,
      "projected_soc_percent": 86.84,
      "pv_forecast_kwh": 0.02,
      "reason": "no_action_needed",
      "slot_number": 36,
      "soc_target_percent": 86.84,
      "start_time": "2025-11-04T08:45:00+01:00",
      "water_from_battery_kwh": 0,
      "water_from_grid_kwh": 0,
      "water_from_pv_kwh": 0,
      "water_heating_kw": 0
    },
    {
      "adjusted_load_kwh": 0.32,
      "adjusted_pv_kwh": 0.02,
      "battery_charge_kw": 0,
      "battery_discharge_kw": 0,
      "charge_kw": 0,
      "classification": "hold",
      "end_time": "2025-11-04T09:15:00+01:00",
      "export_kwh": 0,
      "export_price_sek_kwh": 0.14,
      "export_revenue": 0,
      "import_price_sek_kwh": 1.03,
      "is_cheap": true,
      "load_forecast_kwh": 0.3,
      "priority": "low",
      "projected_battery_cost": 0.2,
      "projected_soc_kwh": 29.52,
      "projected_soc_percent": 86.84,
      "pv_forecast_kwh": 0.02,
      "reason": "no_action_needed",
      "slot_number": 37,
      "soc_target_percent": 86.84,
      "start_time": "2025-11-04T09:00:00+01:00",
      "water_from_battery_kwh": 0,
      "water_from_grid_kwh": 0,
      "water_from_pv_kwh": 0,
      "water_heating_kw": 0
    },
    {
      "adjusted_load_kwh": 0.29,
      "adjusted_pv_kwh": 0.02,
      "battery_charge_kw": 0,
      "battery_discharge_kw": 0,
      "charge_kw": 0,
      "classification": "hold",
      "end_time": "2025-11-04T09:30:00+01:00",
      "export_kwh": 0,
      "export_price_sek_kwh": 0.13,
      "export_revenue": 0,
      "import_price_sek_kwh": 1.02,
      "is_cheap": true,
      "load_forecast_kwh": 0.28,
      "priority": "low",
      "projected_battery_cost": 0.2,
      "projected_soc_kwh": 29.52,
      "projected_soc_percent": 86.84,
      "pv_forecast_kwh": 0.03,
      "reason": "no_action_needed",
      "slot_number": 38,
      "soc_target_percent": 86.84,
      "start_time": "2025-11-04T09:15:00+01:00",
      "water_from_battery_kwh": 0,
      "water_from_grid_kwh": 0,
      "water_from_pv_kwh": 0,
      "water_heating_kw": 0
    },
    {
      "adjusted_load_kwh": 0.31,
      "adjusted_pv_kwh": 0.03,
      "battery_charge_kw": 0,
      "battery_discharge_kw": 0,
      "charge_kw": 0,
      "classification": "hold",
      "end_time": "2025-11-04T09:45:00+01:00",
      "export_kwh": 0,
      "export_price_sek_kwh": 0.1,
      "export_revenue": 0,
      "import_price_sek_kwh": 0.98,
      "is_cheap": true,
      "load_forecast_kwh": 0.3,
      "priority": "low",
      "projected_battery_cost": 0.2,
      "projected_soc_kwh": 29.52,
      "projected_soc_percent": 86.84,
      "pv_forecast_kwh": 0.03,
      "reason": "no_action_needed",
      "slot_number": 39,
      "soc_target_percent": 86.84,
      "start_time": "2025-11-04T09:30:00+01:00",
      "water_from_battery_kwh": 0,
      "water_from_grid_kwh": 0,
      "water_from_pv_kwh": 0,
      "water_heating_kw": 0
    },
    {
      "adjusted_load_kwh": 0.36,
      "adjusted_pv_kwh": 0.03,
      "battery_charge_kw": 0,
      "battery_discharge_kw": 0,
      "charge_kw": 0,
      "classification": "hold",
      "end_time": "2025-11-04T10:00:00+01:00",
      "export_kwh": 0,
      "export_price_sek_kwh": 0.1,
      "export_revenue": 0,
      "import_price_sek_kwh": 0.98,
      "is_cheap": true,
      "load_forecast_kwh": 0.34,
      "priority": "low",
      "projected_battery_cost": 0.2,
      "projected_soc_kwh": 29.52,
      "projected_soc_percent": 86.84,
      "pv_forecast_kwh": 0.03,
      "reason": "no_action_needed",
      "slot_number": 40,
      "soc_target_percent": 86.84,
      "start_time": "2025-11-04T09:45:00+01:00",
      "water_from_battery_kwh": 0,
      "water_from_grid_kwh": 0,
      "water_from_pv_kwh": 0,
      "water_heating_kw": 0
    },
    {
      "adjusted_load_kwh": 0.25,
      "adjusted_pv_kwh": 0.04,
      "battery_charge_kw": 0,
      "battery_discharge_kw": 0,
      "charge_kw": 0,
      "classification": "hold",
      "end_time": "2025-11-04T10:15:00+01:00",
      "export_kwh": 0,
      "export_price_sek_kwh": 0.1,
      "export_revenue": 0,
      "import_price_sek_kwh": 0.98,
      "is_cheap": true,
      "load_forecast_kwh": 0.24,
      "priority": "low",
      "projected_battery_cost": 0.2,
      "projected_soc_kwh": 29.52,
      "projected_soc_percent": 86.84,
      "pv_forecast_kwh": 0.04,
      "reason": "no_action_needed",
      "slot_number": 41,
      "soc_target_percent": 86.84,
      "start_time": "2025-11-04T10:00:00+01:00",
      "water_from_battery_kwh": 0,
      "water_from_grid_kwh": 0,
      "water_from_pv_kwh": 0,
      "water_heating_kw": 0
    },
    {
      "adjusted_load_kwh": 0.24,
      "adjusted_pv_kwh": 0.04,
      "battery_charge_kw": 0,
      "battery_discharge_kw": 0,
      "charge_kw": 0,
      "classification": "hold",
      "end_time": "2025-11-04T10:30:00+01:00",
      "export_kwh": 0,
      "export_price_sek_kwh": 0.1,
      "export_revenue": 0,
      "import_price_sek_kwh": 0.98,
      "is_cheap": true,
      "load_forecast_kwh": 0.23,
      "priority": "low",
      "projected_battery_cost": 0.2,
      "projected_soc_kwh": 29.52,
      "projected_soc_percent": 86.84,
      "pv_forecast_kwh": 0.04,
      "reason": "no_action_needed",
      "slot_number": 42,
      "soc_target_percent": 86.84,
      "start_time": "2025-11-04T10:15:00+01:00",
      "water_from_battery_kwh": 0,
      "water_from_grid_kwh": 0,
      "water_from_pv_kwh": 0,
      "water_heating_kw": 0
    },
    {
      "adjusted_load_kwh": 0.23,
      "adjusted_pv_kwh": 0.05,
      "battery_charge_kw": 0,
      "battery_discharge_kw": 0,
      "charge_kw": 0,
      "classification": "hold",
      "end_time": "2025-11-04T10:45:00+01:00",
      "export_kwh": 0,
      "export_price_sek_kwh": 0.1,
      "export_revenue": 0,
      "import_price_sek_kwh": 0.98,
      "is_cheap": true,
      "load_forecast_kwh": 0.21,
      "priority": "low",
      "projected_battery_cost": 0.2,
      "projected_soc_kwh": 29.52,
      "projected_soc_percent": 86.84,
      "pv_forecast_kwh": 0.05,
      "reason": "no_action_needed",
      "slot_number": 43,
      "soc_target_percent": 86.84,
      "start_time": "2025-11-04T10:30:00+01:00",
      "water_from_battery_kwh": 0,
      "water_from_grid_kwh": 0,
      "water_from_pv_kwh": 0,
      "water_heating_kw": 0
    },
    {
      "adjusted_load_kwh": 0.28,
      "adjusted_pv_kwh": 0.06,
      "battery_charge_kw": 0,
      "battery_discharge_kw": 0,
      "charge_kw": 0,
      "classification": "hold",
      "end_time": "2025-11-04T11:00:00+01:00",
      "export_kwh": 0,
      "export_price_sek_kwh": 0.08,
      "export_revenue": 0,
      "import_price_sek_kwh": 0.96,
      "is_cheap": true,
      "load_forecast_kwh": 0.27,
      "priority": "low",
      "projected_battery_cost": 0.2,
      "projected_soc_kwh": 29.52,
      "projected_soc_percent": 86.84,
      "pv_forecast_kwh": 0.07,
      "reason": "no_action_needed",
      "slot_number": 44,
      "soc_target_percent": 86.84,
      "start_time": "2025-11-04T10:45:00+01:00",
      "water_from_battery_kwh": 0,
      "water_from_grid_kwh": 0,
      "water_from_pv_kwh": 0,
      "water_heating_kw": 0
    },
    {
      "adjusted_load_kwh": 0.25,
      "adjusted_pv_kwh": 0.08,
      "battery_charge_kw": 0,
      "battery_discharge_kw": 0,
      "charge_kw": 0,
      "classification": "hold",
      "end_time": "2025-11-04T11:15:00+01:00",
      "export_kwh": 0,
      "export_price_sek_kwh": 0.09,
      "export_revenue": 0,
      "import_price_sek_kwh": 0.96,
      "is_cheap": true,
      "load_forecast_kwh": 0.24,
      "priority": "low",
      "projected_battery_cost": 0.2,
      "projected_soc_kwh": 29.52,
      "projected_soc_percent": 86.84,
      "pv_forecast_kwh": 0.08,
      "reason": "no_action_needed",
      "slot_number": 45,
      "soc_target_percent": 86.84,
      "start_time": "2025-11-04T11:00:00+01:00",
      "water_from_battery_kwh": 0,
      "water_from_grid_kwh": 0,
      "water_from_pv_kwh": 0,
      "water_heating_kw": 0
    },
    {
      "adjusted_load_kwh": 0.29,
      "adjusted_pv_kwh": 0.09,
      "battery_charge_kw": 0,
      "battery_discharge_kw": 0,
      "charge_kw": 0,
      "classification": "hold",
      "end_time": "2025-11-04T11:30:00+01:00",
      "export_kwh": 0,
      "export_price_sek_kwh": 0.07,
      "export_revenue": 0,
      "import_price_sek_kwh": 0.95,
      "is_cheap": true,
      "load_forecast_kwh": 0.28,
      "priority": "low",
      "projected_battery_cost": 0.2,
      "projected_soc_kwh": 29.52,
      "projected_soc_percent": 86.84,
      "pv_forecast_kwh": 0.09,
      "reason": "no_action_needed",
      "slot_number": 46,
      "soc_target_percent": 86.84,
      "start_time": "2025-11-04T11:15:00+01:00",
      "water_from_battery_kwh": 0,
      "water_from_grid_kwh": 0,
      "water_from_pv_kwh": 0,
      "water_heating_kw": 0
    },
    {
      "adjusted_load_kwh": 0.26,
      "adjusted_pv_kwh": 0.1,
      "battery_charge_kw": 0,
      "battery_discharge_kw": 0,
      "charge_kw": 0,
      "classification": "hold",
      "end_time": "2025-11-04T11:45:00+01:00",
      "export_kwh": 0,
      "export_price_sek_kwh": 0.07,
      "export_revenue": 0,
      "import_price_sek_kwh": 0.95,
      "is_cheap": true,
      "load_forecast_kwh": 0.24,
      "priority": "low",
      "projected_battery_cost": 0.2,
      "projected_soc_kwh": 29.52,
      "projected_soc_percent": 86.84,
      "pv_forecast_kwh": 0.1,
      "reason": "no_action_needed",
      "slot_number": 47,
      "soc_target_percent": 86.84,
      "start_time": "2025-11-04T11:30:00+01:00",
      "water_from_battery_kwh": 0,
      "water_from_grid_kwh": 0,
      "water_from_pv_kwh": 0,
      "water_heating_kw": 0
    },
    {
      "adjusted_load_kwh": 0.25,
      "adjusted_pv_kwh": 0.11,
      "battery_charge_kw": 0,
      "battery_discharge_kw": 0,
      "charge_kw": 0,
      "classification": "hold",
      "end_time": "2025-11-04T12:00:00+01:00",
      "export_kwh": 0,
      "export_price_sek_kwh": 0.07,
      "export_revenue": 0,
      "import_price_sek_kwh": 0.95,
      "is_cheap": true,
      "load_forecast_kwh": 0.24,
      "priority": "low",
      "projected_battery_cost": 0.2,
      "projected_soc_kwh": 29.52,
      "projected_soc_percent": 86.84,
      "pv_forecast_kwh": 0.12,
      "reason": "no_action_needed",
      "slot_number": 48,
      "soc_target_percent": 86.84,
      "start_time": "2025-11-04T11:45:00+01:00",
      "water_from_battery_kwh": 0,
      "water_from_grid_kwh": 0,
      "water_from_pv_kwh": 0,
      "water_heating_kw": 0
    },
    {
      "adjusted_load_kwh": 0.34,
      "adjusted_pv_kwh": 0.12,
      "battery_charge_kw": 0,
      "battery_discharge_kw": 0,
      "charge_kw": 0,
      "classification": "hold",
      "end_time": "2025-11-04T12:15:00+01:00",
      "export_kwh": 0,
      "export_price_sek_kwh": 0.04,
      "export_revenue": 0,
      "import_price_sek_kwh": 0.91,
      "is_cheap": true,
      "load_forecast_kwh": 0.32,
      "priority": "low",
      "projected_battery_cost": 0.2,
      "projected_soc_kwh": 29.52,
      "projected_soc_percent": 86.84,
      "pv_forecast_kwh": 0.13,
      "reason": "no_action_needed",
      "slot_number": 49,
      "soc_target_percent": 86.84,
      "start_time": "2025-11-04T12:00:00+01:00",
      "water_from_battery_kwh": 0,
      "water_from_grid_kwh": 0,
      "water_from_pv_kwh": 0,
      "water_heating_kw": 0
    },
    {
      "adjusted_load_kwh": 0.36,
      "adjusted_pv_kwh": 0.12,
      "battery_charge_kw": 0,
      "battery_discharge_kw": 0,
      "charge_kw": 0,
      "classification": "hold",
      "end_time": "2025-11-04T12:30:00+01:00",
      "export_kwh": 0,
      "export_price_sek_kwh": 0.04,
      "export_revenue": 0,
      "import_price_sek_kwh": 0.9,
      "is_cheap": true,
      "load_forecast_kwh": 0.34,
      "priority": "low",
      "projected_battery_cost": 0.2,
      "projected_soc_kwh": 29.52,
      "projected_soc_percent": 86.84,
      "pv_forecast_kwh": 0.13,
      "reason": "no_action_needed",
      "slot_number": 50,
      "soc_target_percent": 86.84,
      "start_time": "2025-11-04T12:15:00+01:00",
      "water_from_battery_kwh": 0,
      "water_from_grid_kwh": 0,
      "water_from_pv_kwh": 0,
      "water_heating_kw": 0
    },
    {
      "adjusted_load_kwh": 0.43,
      "adjusted_pv_kwh": 0.12,
      "battery_charge_kw": 0,
      "battery_discharge_kw": 0,
      "charge_kw": 0,
      "classification": "hold",
      "end_time": "2025-11-04T12:45:00+01:00",
      "export_kwh": 0,
      "export_price_sek_kwh": 0.03,
      "export_revenue": 0,
      "import_price_sek_kwh": 0.9,
      "is_cheap": true,
      "load_forecast_kwh": 0.41,
      "priority": "low",
      "projected_battery_cost": 0.2,
      "projected_soc_kwh": 29.52,
      "projected_soc_percent": 86.84,
      "pv_forecast_kwh": 0.12,
      "reason": "no_action_needed",
      "slot_number": 51,
      "soc_target_percent": 86.84,
      "start_time": "2025-11-04T12:30:00+01:00",
      "water_from_battery_kwh": 0,
      "water_from_grid_kwh": 0,
      "water_from_pv_kwh": 0,
      "water_heating_kw": 0
    },
    {
      "adjusted_load_kwh": 0.36,
      "adjusted_pv_kwh": 0.1,
      "battery_charge_kw": 0,
      "battery_discharge_kw": 0,
      "charge_kw": 0,
      "classification": "hold",
      "end_time": "2025-11-04T13:00:00+01:00",
      "export_kwh": 0,
      "export_price_sek_kwh": 0.04,
      "export_revenue": 0,
      "import_price_sek_kwh": 0.9,
      "is_cheap": true,
      "load_forecast_kwh": 0.34,
      "priority": "low",
      "projected_battery_cost": 0.2,
      "projected_soc_kwh": 29.52,
      "projected_soc_percent": 86.84,
      "pv_forecast_kwh": 0.11,
      "reason": "no_action_needed",
      "slot_number": 52,
      "soc_target_percent": 86.84,
      "start_time": "2025-11-04T12:45:00+01:00",
      "water_from_battery_kwh": 0,
      "water_from_grid_kwh": 0,
      "water_from_pv_kwh": 0,
      "water_heating_kw": 0
    },
    {
      "adjusted_load_kwh": 0.44,
      "adjusted_pv_kwh": 0.08,
      "battery_charge_kw": 0,
      "battery_discharge_kw": 0,
      "charge_kw": 0,
      "classification": "hold",
      "end_time": "2025-11-04T13:15:00+01:00",
      "export_kwh": 0,
      "export_price_sek_kwh": 0.07,
      "export_revenue": 0,
      "import_price_sek_kwh": 0.94,
      "is_cheap": true,
      "load_forecast_kwh": 0.42,
      "priority": "low",
      "projected_battery_cost": 0.2,
      "projected_soc_kwh": 29.52,
      "projected_soc_percent": 86.84,
      "pv_forecast_kwh": 0.09,
      "reason": "no_action_needed",
      "slot_number": 53,
      "soc_target_percent": 86.84,
      "start_time": "2025-11-04T13:00:00+01:00",
      "water_from_battery_kwh": 0,
      "water_from_grid_kwh": 0,
      "water_from_pv_kwh": 0,
      "water_heating_kw": 0
    },
    {
      "adjusted_load_kwh": 0.41,
      "adjusted_pv_kwh": 0.07,
      "battery_charge_kw": 0,
      "battery_discharge_kw": 0,
      "charge_kw": 0,
      "classification": "hold",
      "end_time": "2025-11-04T13:30:00+01:00",
      "export_kwh": 0,
      "export_price_sek_kwh": 0.07,
      "export_revenue": 0,
      "import_price_sek_kwh": 0.95,
      "is_cheap": true,
      "load_forecast_kwh": 0.39,
      "priority": "low",
      "projected_battery_cost": 0.2,
      "projected_soc_kwh": 29.52,
      "projected_soc_percent": 86.84,
      "pv_forecast_kwh": 0.07,
      "reason": "no_action_needed",
      "slot_number": 54,
      "soc_target_percent": 86.84,
      "start_time": "2025-11-04T13:15:00+01:00",
      "water_from_battery_kwh": 0,
      "water_from_grid_kwh": 0,
      "water_from_pv_kwh": 0,
      "water_heating_kw": 0
    },
    {
      "adjusted_load_kwh": 0.27,
      "adjusted_pv_kwh": 0.05,
      "battery_charge_kw": 0,
      "battery_discharge_kw": 0,
      "charge_kw": 0,
      "classification": "hold",
      "end_time": "2025-11-04T13:45:00+01:00",
      "export_kwh": 0,
      "export_price_sek_kwh": 0.07,
      "export_revenue": 0,
      "import_price_sek_kwh": 0.95,
      "is_cheap": true,
      "load_forecast_kwh": 0.26,
      "priority": "low",
      "projected_battery_cost": 0.2,
      "projected_soc_kwh": 29.52,
      "projected_soc_percent": 86.84,
      "pv_forecast_kwh": 0.06,
      "reason": "no_action_needed",
      "slot_number": 55,
      "soc_target_percent": 86.84,
      "start_time": "2025-11-04T13:30:00+01:00",
      "water_from_battery_kwh": 0,
      "water_from_grid_kwh": 0,
      "water_from_pv_kwh": 0,
      "water_heating_kw": 0
    },
    {
      "adjusted_load_kwh": 0.21,
      "adjusted_pv_kwh": 0.05,
      "battery_charge_kw": 0,
      "battery_discharge_kw": 0,
      "charge_kw": 0,
      "classification": "hold",
      "end_time": "2025-11-04T14:00:00+01:00",
      "export_kwh": 0,
      "export_price_sek_kwh": 0.07,
      "export_revenue": 0,
      "import_price_sek_kwh": 0.95,
      "is_cheap": true,
      "load_forecast_kwh": 0.2,
      "priority": "low",
      "projected_battery_cost": 0.2,
      "projected_soc_kwh": 29.52,
      "projected_soc_percent": 86.84,
      "pv_forecast_kwh": 0.05,
      "reason": "no_action_needed",
      "slot_number": 56,
      "soc_target_percent": 86.84,
      "start_time": "2025-11-04T13:45:00+01:00",
      "water_from_battery_kwh": 0,
      "water_from_grid_kwh": 0,
      "water_from_pv_kwh": 0,
      "water_heating_kw": 0
    },
    {
      "adjusted_load_kwh": 0.22,
      "adjusted_pv_kwh": 0.04,
      "battery_charge_kw": 0,
      "battery_discharge_kw": 0,
      "charge_kw": 0,
      "classification": "hold",
      "end_time": "2025-11-04T14:15:00+01:00",
      "export_kwh": 0,
      "export_price_sek_kwh": 0.08,
      "export_revenue": 0,
      "import_price_sek_kwh": 0.96,
      "is_cheap": true,
      "load_forecast_kwh": 0.21,
      "priority": "low",
      "projected_battery_cost": 0.2,
      "projected_soc_kwh": 29.52,
      "projected_soc_percent": 86.84,
      "pv_forecast_kwh": 0.05,
      "reason": "no_action_needed",
      "slot_number": 57,
      "soc_target_percent": 86.84,
      "start_time": "2025-11-04T14:00:00+01:00",
      "water_from_battery_kwh": 0,
      "water_from_grid_kwh": 0,
      "water_from_pv_kwh": 0,
      "water_heating_kw": 0
    },
    {
      "adjusted_load_kwh": 0.21,
      "adjusted_pv_kwh": 0.04,
      "battery_charge_kw": 0,
      "battery_discharge_kw": 0,
      "charge_kw": 0,
      "classification": "hold",
      "end_time": "2025-11-04T14:30:00+01:00",
      "export_kwh": 0,
      "export_price_sek_kwh": 0.09,
      "export_revenue": 0,
      "import_price_sek_kwh": 0.97,
      "is_cheap": true,
      "load_forecast_kwh": 0.2,
      "priority": "low",
      "projected_battery_cost": 0.2,
      "projected_soc_kwh": 29.52,
      "projected_soc_percent": 86.84,
      "pv_forecast_kwh": 0.04,
      "reason": "no_action_needed",
      "slot_number": 58,
      "soc_target_percent": 86.84,
      "start_time": "2025-11-04T14:15:00+01:00",
      "water_from_battery_kwh": 0,
      "water_from_grid_kwh": 0,
      "water_from_pv_kwh": 0,
      "water_heating_kw": 0
    },
    {
      "adjusted_load_kwh": 0.33,
      "adjusted_pv_kwh": 0.03,
      "battery_charge_kw": 0,
      "battery_discharge_kw": 0,
      "charge_kw": 0,
      "classification": "hold",
      "end_time": "2025-11-04T14:45:00+01:00",
      "export_kwh": 0,
      "export_price_sek_kwh": 0.09,
      "export_revenue": 0,
      "import_price_sek_kwh": 0.96,
      "is_cheap": true,
      "load_forecast_kwh": 0.31,
      "priority": "low",
      "projected_battery_cost": 0.2,
      "projected_soc_kwh": 29.52,
      "projected_soc_percent": 86.84,
      "pv_forecast_kwh": 0.04,
      "reason": "no_action_needed",
      "slot_number": 59,
      "soc_target_percent": 86.84,
      "start_time": "2025-11-04T14:30:00+01:00",
      "water_from_battery_kwh": 0,
      "water_from_grid_kwh": 0,
      "water_from_pv_kwh": 0,
      "water_heating_kw": 0
    },
    {
      "adjusted_load_kwh": 0.29,
      "adjusted_pv_kwh": 0.03,
      "battery_charge_kw": 0,
      "battery_discharge_kw": 0,
      "charge_kw": 0,
      "classification": "hold",
      "end_time": "2025-11-04T15:00:00+01:00",
      "export_kwh": 0,
      "export_price_sek_kwh": 0.09,
      "export_revenue": 0,
      "import_price_sek_kwh": 0.97,
      "is_cheap": true,
      "load_forecast_kwh": 0.28,
      "priority": "low",
      "projected_battery_cost": 0.2,
      "projected_soc_kwh": 29.52,
      "projected_soc_percent": 86.84,
      "pv_forecast_kwh": 0.03,
      "reason": "no_action_needed",
      "slot_number": 60,
      "soc_target_percent": 86.84,
      "start_time": "2025-11-04T14:45:00+01:00",
      "water_from_battery_kwh": 0,
      "water_from_grid_kwh": 0,
      "water_from_pv_kwh": 0,
      "water_heating_kw": 0
    },
    {
      "adjusted_load_kwh": 0.3,
      "adjusted_pv_kwh": 0.02,
      "battery_charge_kw": 0,
      "battery_discharge_kw": 0,
      "charge_kw": 0,
      "classification": "hold",
      "end_time": "2025-11-04T15:15:00+01:00",
      "export_kwh": 0,
      "export_price_sek_kwh": 0.08,
      "export_revenue": 0,
      "import_price_sek_kwh": 0.95,
      "is_cheap": true,
      "load_forecast_kwh": 0.28,
      "priority": "low",
      "projected_battery_cost": 0.2,
      "projected_soc_kwh": 29.52,
      "projected_soc_percent": 86.84,
      "pv_forecast_kwh": 0.03,
      "reason": "no_action_needed",
      "slot_number": 61,
      "soc_target_percent": 86.84,
      "start_time": "2025-11-04T15:00:00+01:00",
      "water_from_battery_kwh": 0,
      "water_from_grid_kwh": 0,
      "water_from_pv_kwh": 0,
      "water_heating_kw": 0
    },
    {
      "adjusted_load_kwh": 0.31,
      "adjusted_pv_kwh": 0.02,
      "battery_charge_kw": 0,
      "battery_discharge_kw": 0,
      "charge_kw": 0,
      "classification": "hold",
      "end_time": "2025-11-04T15:30:00+01:00",
      "export_kwh": 0,
      "export_price_sek_kwh": 0.09,
      "export_revenue": 0,
      "import_price_sek_kwh": 0.97,
      "is_cheap": true,
      "load_forecast_kwh": 0.3,
      "priority": "low",
      "projected_battery_cost": 0.2,
      "projected_soc_kwh": 29.52,
      "projected_soc_percent": 86.84,
      "pv_forecast_kwh": 0.02,
      "reason": "no_action_needed",
      "slot_number": 62,
      "soc_target_percent": 86.84,
      "start_time": "2025-11-04T15:15:00+01:00",
      "water_from_battery_kwh": 0,
      "water_from_grid_kwh": 0,
      "water_from_pv_kwh": 0,
      "water_heating_kw": 0
    },
    {
      "adjusted_load_kwh": 0.28,
      "adjusted_pv_kwh": 0.01,
      "battery_charge_kw": 0,
      "battery_discharge_kw": 0,
      "charge_kw": 0,
      "classification": "hold",
      "end_time": "2025-11-04T15:45:00+01:00",
      "export_kwh": 0,
      "export_price_sek_kwh": 0.11,
      "export_revenue": 0,
      "import_price_sek_kwh": 1,
      "is_cheap": true,
      "load_forecast_kwh": 0.27,
      "priority": "low",
      "projected_battery_cost": 0.2,
      "projected_soc_kwh": 29.52,
      "projected_soc_percent": 86.84,
      "pv_forecast_kwh": 0.01,
      "reason": "no_action_needed",
      "slot_number": 63,
      "soc_target_percent": 86.84,
      "start_time": "2025-11-04T15:30:00+01:00",
      "water_from_battery_kwh": 0,
      "water_from_grid_kwh": 0,
      "water_from_pv_kwh": 0,
      "water_heating_kw": 0
    },
    {
      "adjusted_load_kwh": 0.24,
      "adjusted_pv_kwh": 0,
      "battery_charge_kw": 0,
      "battery_discharge_kw": 0,
      "charge_kw": 0,
      "classification": "hold",
      "end_time": "2025-11-04T16:00:00+01:00",
      "export_kwh": 0,
      "export_price_sek_kwh": 0.13,
      "export_revenue": 0,
      "import_price_sek_kwh": 1.01,
      "is_cheap": true,
      "load_forecast_kwh": 0.23,
      "priority": "low",
      "projected_battery_cost": 0.2,
      "projected_soc_kwh": 29.52,
      "projected_soc_percent": 86.84,
      "pv_forecast_kwh": 0,
      "reason": "no_action_needed",
      "slot_number": 64,
      "soc_target_percent": 86.84,
      "start_time": "2025-11-04T15:45:00+01:00",
      "water_from_battery_kwh": 0,
      "water_from_grid_kwh": 0,
      "water_from_pv_kwh": 0,
      "water_heating_kw": 0
    },
    {
      "adjusted_load_kwh": 0.2,
      "adjusted_pv_kwh": 0,
      "battery_charge_kw": 0,
      "battery_discharge_kw": 0.82,
      "charge_kw": 0,
      "classification": "discharge",
      "end_time": "2025-11-04T16:15:00+01:00",
      "export_kwh": 0,
      "export_price_sek_kwh": 0.13,
      "export_revenue": 0,
      "import_price_sek_kwh": 1.02,
      "is_cheap": true,
      "load_forecast_kwh": 0.19,
      "priority": "high",
      "projected_battery_cost": 0.2,
      "projected_soc_kwh": 29.31,
      "projected_soc_percent": 86.22,
      "pv_forecast_kwh": 0,
      "reason": "expensive_grid_power",
      "slot_number": 65,
      "soc_target_percent": 15,
      "start_time": "2025-11-04T16:00:00+01:00",
      "water_from_battery_kwh": 0,
      "water_from_grid_kwh": 0,
      "water_from_pv_kwh": 0,
      "water_heating_kw": 0
    },
    {
      "adjusted_load_kwh": 0.23,
      "adjusted_pv_kwh": 0,
      "battery_charge_kw": 0,
      "battery_discharge_kw": 0.91,
      "charge_kw": 0,
      "classification": "discharge",
      "end_time": "2025-11-04T16:30:00+01:00",
      "export_kwh": 0,
      "export_price_sek_kwh": 0.14,
      "export_revenue": 0,
      "import_price_sek_kwh": 1.04,
      "is_cheap": true,
      "load_forecast_kwh": 0.22,
      "priority": "high",
      "projected_battery_cost": 0.2,
      "projected_soc_kwh": 29.08,
      "projected_soc_percent": 85.53,
      "pv_forecast_kwh": 0,
      "reason": "expensive_grid_power",
      "slot_number": 66,
      "soc_target_percent": 15,
      "start_time": "2025-11-04T16:15:00+01:00",
      "water_from_battery_kwh": 0,
      "water_from_grid_kwh": 0,
      "water_from_pv_kwh": 0,
      "water_heating_kw": 0
    },
    {
      "adjusted_load_kwh": 0.2,
      "adjusted_pv_kwh": 0,
      "battery_charge_kw": 0,
      "battery_discharge_kw": 0.79,
      "charge_kw": 0,
      "classification": "discharge",
      "end_time": "2025-11-04T16:45:00+01:00",
      "export_kwh": 0,
      "export_price_sek_kwh": 0.15,
      "export_revenue": 0,
      "import_price_sek_kwh": 1.04,
      "is_cheap": true,
      "load_forecast_kwh": 0.19,
      "priority": "high",
      "projected_battery_cost": 0.2,
      "projected_soc_kwh": 28.88,
      "projected_soc_percent": 84.94,
      "pv_forecast_kwh": 0,
      "reason": "expensive_grid_power",
      "slot_number": 67,
      "soc_target_percent": 15,
      "start_time": "2025-11-04T16:30:00+01:00",
      "water_from_battery_kwh": 0,
      "water_from_grid_kwh": 0,
      "water_from_pv_kwh": 0,
      "water_heating_kw": 0
    },
    {
      "adjusted_load_kwh": 0.2,
      "adjusted_pv_kwh": 0,
      "battery_charge_kw": 0,
      "battery_discharge_kw": 0.81,
      "charge_kw": 0,
      "classification": "discharge",
      "end_time": "2025-11-04T17:00:00+01:00",
      "export_kwh": 0,
      "export_price_sek_kwh": 0.15,
      "export_revenue": 0,
      "import_price_sek_kwh": 1.04,
      "is_cheap": true,
      "load_forecast_kwh": 0.19,
      "priority": "high",
      "projected_battery_cost": 0.2,
      "projected_soc_kwh": 28.67,
      "projected_soc_percent": 84.33,
      "pv_forecast_kwh": 0,
      "reason": "expensive_grid_power",
      "slot_number": 68,
      "soc_target_percent": 15,
      "start_time": "2025-11-04T16:45:00+01:00",
      "water_from_battery_kwh": 0,
      "water_from_grid_kwh": 0,
      "water_from_pv_kwh": 0,
      "water_heating_kw": 0
    },
    {
      "adjusted_load_kwh": 0.3,
      "adjusted_pv_kwh": 0,
      "battery_charge_kw": 0,
      "battery_discharge_kw": 1.2,
      "charge_kw": 0,
      "classification": "discharge",
      "end_time": "2025-11-04T17:15:00+01:00",
      "export_kwh": 0,
      "export_price_sek_kwh": 0.28,
      "export_revenue": 0,
      "import_price_sek_kwh": 1.2,
      "is_cheap": false,
      "load_forecast_kwh": 0.28,
      "priority": "high",
      "projected_battery_cost": 0.2,
      "projected_soc_kwh": 28.36,
      "projected_soc_percent": 83.43,
      "pv_forecast_kwh": 0,
      "reason": "expensive_grid_power",
      "slot_number": 69,
      "soc_target_percent": 15,
      "start_time": "2025-11-04T17:00:00+01:00",
      "water_from_battery_kwh": 0,
      "water_from_grid_kwh": 0,
      "water_from_pv_kwh": 0,
      "water_heating_kw": 0
    },
    {
      "adjusted_load_kwh": 0.39,
      "adjusted_pv_kwh": 0,
      "battery_charge_kw": 0,
      "battery_discharge_kw": 1.57,
      "charge_kw": 0,
      "classification": "discharge",
      "end_time": "2025-11-04T17:30:00+01:00",
      "export_kwh": 0,
      "export_price_sek_kwh": 0.35,
      "export_revenue": 0,
      "import_price_sek_kwh": 1.3,
      "is_cheap": false,
      "load_forecast_kwh": 0.37,
      "priority": "high",
      "projected_battery_cost": 0.2,
      "projected_soc_kwh": 27.96,
      "projected_soc_percent": 82.24,
      "pv_forecast_kwh": 0,
      "reason": "expensive_grid_power",
      "slot_number": 70,
      "soc_target_percent": 15,
      "start_time": "2025-11-04T17:15:00+01:00",
      "water_from_battery_kwh": 0,
      "water_from_grid_kwh": 0,
      "water_from_pv_kwh": 0,
      "water_heating_kw": 0
    },
    {
      "adjusted_load_kwh": 0.38,
      "adjusted_pv_kwh": 0,
      "battery_charge_kw": 0,
      "battery_discharge_kw": 1.51,
      "charge_kw": 0,
      "classification": "discharge",
      "end_time": "2025-11-04T17:45:00+01:00",
      "export_kwh": 0,
      "export_price_sek_kwh": 0.35,
      "export_revenue": 0,
      "import_price_sek_kwh": 1.3,
      "is_cheap": false,
      "load_forecast_kwh": 0.36,
      "priority": "high",
      "projected_battery_cost": 0.2,
      "projected_soc_kwh": 27.58,
      "projected_soc_percent": 81.11,
      "pv_forecast_kwh": 0,
      "reason": "expensive_grid_power",
      "slot_number": 71,
      "soc_target_percent": 15,
      "start_time": "2025-11-04T17:30:00+01:00",
      "water_from_battery_kwh": 0,
      "water_from_grid_kwh": 0,
      "water_from_pv_kwh": 0,
      "water_heating_kw": 0
    },
    {
      "adjusted_load_kwh": 0.29,
      "adjusted_pv_kwh": 0,
      "battery_charge_kw": 0,
      "battery_discharge_kw": 1.17,
      "charge_kw": 0,
      "classification": "discharge",
      "end_time": "2025-11-04T18:00:00+01:00",
      "export_kwh": 0,
      "export_price_sek_kwh": 0.34,
      "export_revenue": 0,
      "import_price_sek_kwh": 1.28,
      "is_cheap": false,
      "load_forecast_kwh": 0.28,
      "priority": "high",
      "projected_battery_cost": 0.2,
      "projected_soc_kwh": 27.28,
      "projected_soc_percent": 80.23,
      "pv_forecast_kwh": 0,
      "reason": "expensive_grid_power",
      "slot_number": 72,
      "soc_target_percent": 15,
      "start_time": "2025-11-04T17:45:00+01:00",
      "water_from_battery_kwh": 0,
      "water_from_grid_kwh": 0,
      "water_from_pv_kwh": 0,
      "water_heating_kw": 0
    },
    {
      "adjusted_load_kwh": 0.4,
      "adjusted_pv_kwh": 0,
      "battery_charge_kw": 0,
      "battery_discharge_kw": 1.61,
      "charge_kw": 0,
      "classification": "discharge",
      "end_time": "2025-11-04T18:15:00+01:00",
      "export_kwh": 0,
      "export_price_sek_kwh": 0.41,
      "export_revenue": 0,
      "import_price_sek_kwh": 1.37,
      "is_cheap": false,
      "load_forecast_kwh": 0.38,
      "priority": "high",
      "projected_battery_cost": 0.2,
      "projected_soc_kwh": 26.86,
      "projected_soc_percent": 79.01,
      "pv_forecast_kwh": 0,
      "reason": "expensive_grid_power",
      "slot_number": 73,
      "soc_target_percent": 15,
      "start_time": "2025-11-04T18:00:00+01:00",
      "water_from_battery_kwh": 0,
      "water_from_grid_kwh": 0,
      "water_from_pv_kwh": 0,
      "water_heating_kw": 0
    },
    {
      "adjusted_load_kwh": 0.45,
      "adjusted_pv_kwh": 0,
      "battery_charge_kw": 0,
      "battery_discharge_kw": 1.81,
      "charge_kw": 0,
      "classification": "discharge",
      "end_time": "2025-11-04T18:30:00+01:00",
      "export_kwh": 0,
      "export_price_sek_kwh": 0.41,
      "export_revenue": 0,
      "import_price_sek_kwh": 1.37,
      "is_cheap": false,
      "load_forecast_kwh": 0.43,
      "priority": "high",
      "projected_battery_cost": 0.2,
      "projected_soc_kwh": 26.4,
      "projected_soc_percent": 77.65,
      "pv_forecast_kwh": 0,
      "reason": "expensive_grid_power",
      "slot_number": 74,
      "soc_target_percent": 15,
      "start_time": "2025-11-04T18:15:00+01:00",
      "water_from_battery_kwh": 0,
      "water_from_grid_kwh": 0,
      "water_from_pv_kwh": 0,
      "water_heating_kw": 0
    },
    {
      "adjusted_load_kwh": 0.42,
      "adjusted_pv_kwh": 0,
      "battery_charge_kw": 0,
      "battery_discharge_kw": 1.66,
      "charge_kw": 0,
      "classification": "discharge",
      "end_time": "2025-11-04T18:45:00+01:00",
      "export_kwh": 0,
      "export_price_sek_kwh": 0.41,
      "export_revenue": 0,
      "import_price_sek_kwh": 1.37,
      "is_cheap": false,
      "load_forecast_kwh": 0.4,
      "priority": "high",
      "projected_battery_cost": 0.2,
      "projected_soc_kwh": 25.97,
      "projected_soc_percent": 76.4,
      "pv_forecast_kwh": 0,
      "reason": "expensive_grid_power",
      "slot_number": 75,
      "soc_target_percent": 15,
      "start_time": "2025-11-04T18:30:00+01:00",
      "water_from_battery_kwh": 0,
      "water_from_grid_kwh": 0,
      "water_from_pv_kwh": 0,
      "water_heating_kw": 0
    },
    {
      "adjusted_load_kwh": 0.3,
      "adjusted_pv_kwh": 0,
      "battery_charge_kw": 0,
      "battery_discharge_kw": 1.21,
      "charge_kw": 0,
      "classification": "discharge",
      "end_time": "2025-11-04T19:00:00+01:00",
      "export_kwh": 0,
      "export_price_sek_kwh": 0.41,
      "export_revenue": 0,
      "import_price_sek_kwh": 1.36,
      "is_cheap": false,
      "load_forecast_kwh": 0.29,
      "priority": "high",
      "projected_battery_cost": 0.2,
      "projected_soc_kwh": 25.66,
      "projected_soc_percent": 75.48,
      "pv_forecast_kwh": 0,
      "reason": "expensive_grid_power",
      "slot_number": 76,
      "soc_target_percent": 15,
      "start_time": "2025-11-04T18:45:00+01:00",
      "water_from_battery_kwh": 0,
      "water_from_grid_kwh": 0,
      "water_from_pv_kwh": 0,
      "water_heating_kw": 0
    },
    {
      "adjusted_load_kwh": 0.24,
      "adjusted_pv_kwh": 0,
      "battery_charge_kw": 0,
      "battery_discharge_kw": 0.95,
      "charge_kw": 0,
      "classification": "discharge",
      "end_time": "2025-11-04T19:15:00+01:00",
      "export_kwh": 0,
      "export_price_sek_kwh": 0.33,
      "export_revenue": 0,
      "import_price_sek_kwh": 1.27,
      "is_cheap": false,
      "load_forecast_kwh": 0.23,
      "priority": "high",
      "projected_battery_cost": 0.2,
      "projected_soc_kwh": 25.42,
      "projected_soc_percent": 74.77,
      "pv_forecast_kwh": 0,
      "reason": "expensive_grid_power",
      "slot_number": 77,
      "soc_target_percent": 15,
      "start_time": "2025-11-04T19:00:00+01:00",
      "water_from_battery_kwh": 0,
      "water_from_grid_kwh": 0,
      "water_from_pv_kwh": 0,
      "water_heating_kw": 0
    },
    {
      "adjusted_load_kwh": 0.2,
      "adjusted_pv_kwh": 0,
      "battery_charge_kw": 0,
      "battery_discharge_kw": 0.81,
      "charge_kw": 0,
      "classification": "discharge",
      "end_time": "2025-11-04T19:30:00+01:00",
      "export_kwh": 0,
      "export_price_sek_kwh": 0.17,
      "export_revenue": 0,
      "import_price_sek_kwh": 1.07,
      "is_cheap": false,
      "load_forecast_kwh": 0.19,
      "priority": "high",
      "projected_battery_cost": 0.2,
      "projected_soc_kwh": 25.21,
      "projected_soc_percent": 74.15,
      "pv_forecast_kwh": 0,
      "reason": "expensive_grid_power",
      "slot_number": 78,
      "soc_target_percent": 15,
      "start_time": "2025-11-04T19:15:00+01:00",
      "water_from_battery_kwh": 0,
      "water_from_grid_kwh": 0,
      "water_from_pv_kwh": 0,
      "water_heating_kw": 0
    },
    {
      "adjusted_load_kwh": 0.25,
      "adjusted_pv_kwh": 0,
      "battery_charge_kw": 0,
      "battery_discharge_kw": 0,
      "charge_kw": 0,
      "classification": "hold",
      "end_time": "2025-11-04T19:45:00+01:00",
      "export_kwh": 0,
      "export_price_sek_kwh": 0.12,
      "export_revenue": 0,
      "import_price_sek_kwh": 1.01,
      "is_cheap": true,
      "load_forecast_kwh": 0.24,
      "priority": "low",
      "projected_battery_cost": 0.2,
      "projected_soc_kwh": 25.21,
      "projected_soc_percent": 74.15,
      "pv_forecast_kwh": 0,
      "reason": "no_action_needed",
      "slot_number": 79,
      "soc_target_percent": 74.15,
      "start_time": "2025-11-04T19:30:00+01:00",
      "water_from_battery_kwh": 0,
      "water_from_grid_kwh": 0,
      "water_from_pv_kwh": 0,
      "water_heating_kw": 0
    },
    {
      "adjusted_load_kwh": 0.27,
      "adjusted_pv_kwh": 0,
      "battery_charge_kw": 0,
      "battery_discharge_kw": 0,
      "charge_kw": 0,
      "classification": "hold",
      "end_time": "2025-11-04T20:00:00+01:00",
      "export_kwh": 0,
      "export_price_sek_kwh": 0.12,
      "export_revenue": 0,
      "import_price_sek_kwh": 1.01,
      "is_cheap": true,
      "load_forecast_kwh": 0.26,
      "priority": "low",
      "projected_battery_cost": 0.2,
      "projected_soc_kwh": 25.21,
      "projected_soc_percent": 74.15,
      "pv_forecast_kwh": 0,
      "reason": "no_action_needed",
      "slot_number": 80,
      "soc_target_percent": 74.15,
      "start_time": "2025-11-04T19:45:00+01:00",
      "water_from_battery_kwh": 0,
      "water_from_grid_kwh": 0,
      "water_from_pv_kwh": 0,
      "water_heating_kw": 0
    },
    {
      "adjusted_load_kwh": 0.28,
      "adjusted_pv_kwh": 0,
      "battery_charge_kw": 0,
      "battery_discharge_kw": 0,
      "charge_kw": 0,
      "classification": "hold",
      "end_time": "2025-11-04T20:15:00+01:00",
      "export_kwh": 0,
      "export_price_sek_kwh": 0.07,
      "export_revenue": 0,
      "import_price_sek_kwh": 0.94,
      "is_cheap": true,
      "load_forecast_kwh": 0.27,
      "priority": "low",
      "projected_battery_cost": 0.2,
      "projected_soc_kwh": 25.21,
      "projected_soc_percent": 74.15,
      "pv_forecast_kwh": 0,
      "reason": "no_action_needed",
      "slot_number": 81,
      "soc_target_percent": 74.15,
      "start_time": "2025-11-04T20:00:00+01:00",
      "water_from_battery_kwh": 0,
      "water_from_grid_kwh": 0,
      "water_from_pv_kwh": 0,
      "water_heating_kw": 0
    },
    {
      "adjusted_load_kwh": 0.22,
      "adjusted_pv_kwh": 0,
      "battery_charge_kw": 0,
      "battery_discharge_kw": 0,
      "charge_kw": 0,
      "classification": "hold",
      "end_time": "2025-11-04T20:30:00+01:00",
      "export_kwh": 0,
      "export_price_sek_kwh": 0.08,
      "export_revenue": 0,
      "import_price_sek_kwh": 0.96,
      "is_cheap": true,
      "load_forecast_kwh": 0.21,
      "priority": "low",
      "projected_battery_cost": 0.2,
      "projected_soc_kwh": 25.21,
      "projected_soc_percent": 74.15,
      "pv_forecast_kwh": 0,
      "reason": "no_action_needed",
      "slot_number": 82,
      "soc_target_percent": 74.15,
      "start_time": "2025-11-04T20:15:00+01:00",
      "water_from_battery_kwh": 0,
      "water_from_grid_kwh": 0,
      "water_from_pv_kwh": 0,
      "water_heating_kw": 0
    },
    {
      "adjusted_load_kwh": 0.26,
      "adjusted_pv_kwh": 0,
      "battery_charge_kw": 0,
      "battery_discharge_kw": 0,
      "charge_kw": 0,
      "classification": "hold",
      "end_time": "2025-11-04T20:45:00+01:00",
      "export_kwh": 0,
      "export_price_sek_kwh": 0.08,
      "export_revenue": 0,
      "import_price_sek_kwh": 0.96,
      "is_cheap": true,
      "load_forecast_kwh": 0.25,
      "priority": "low",
      "projected_battery_cost": 0.2,
      "projected_soc_kwh": 25.21,
      "projected_soc_percent": 74.15,
      "pv_forecast_kwh": 0,
      "reason": "no_action_needed",
      "slot_number": 83,
      "soc_target_percent": 74.15,
      "start_time": "2025-11-04T20:30:00+01:00",
      "water_from_battery_kwh": 0,
      "water_from_grid_kwh": 0,
      "water_from_pv_kwh": 0,
      "water_heating_kw": 0
    },
    {
      "adjusted_load_kwh": 0.21,
      "adjusted_pv_kwh": 0,
      "battery_charge_kw": 0,
      "battery_discharge_kw": 0,
      "charge_kw": 0,
      "classification": "hold",
      "end_time": "2025-11-04T21:00:00+01:00",
      "export_kwh": 0,
      "export_price_sek_kwh": 0.08,
      "export_revenue": 0,
      "import_price_sek_kwh": 0.96,
      "is_cheap": true,
      "load_forecast_kwh": 0.2,
      "priority": "low",
      "projected_battery_cost": 0.2,
      "projected_soc_kwh": 25.21,
      "projected_soc_percent": 74.15,
      "pv_forecast_kwh": 0,
      "reason": "no_action_needed",
      "slot_number": 84,
      "soc_target_percent": 74.15,
      "start_time": "2025-11-04T20:45:00+01:00",
      "water_from_battery_kwh": 0,
      "water_from_grid_kwh": 0,
      "water_from_pv_kwh": 0,
      "water_heating_kw": 0
    },
    {
      "adjusted_load_kwh": 0.26,
      "adjusted_pv_kwh": 0,
      "battery_charge_kw": 0,
      "battery_discharge_kw": 0,
      "charge_kw": 0,
      "classification": "hold",
      "end_time": "2025-11-04T21:15:00+01:00",
      "export_kwh": 0,
      "export_price_sek_kwh": 0.08,
      "export_revenue": 0,
      "import_price_sek_kwh": 0.96,
      "is_cheap": true,
      "load_forecast_kwh": 0.24,
      "priority": "low",
      "projected_battery_cost": 0.2,
      "projected_soc_kwh": 25.21,
      "projected_soc_percent": 74.15,
      "pv_forecast_kwh": 0,
      "reason": "no_action_needed",
      "slot_number": 85,
      "soc_target_percent": 74.15,
      "start_time": "2025-11-04T21:00:00+01:00",
      "water_from_battery_kwh": 0,
      "water_from_grid_kwh": 0,
      "water_from_pv_kwh": 0,
      "water_heating_kw": 0
    },
    {
      "adjusted_load_kwh": 0.31,
      "adjusted_pv_kwh": 0,
      "battery_charge_kw": 0,
      "battery_discharge_kw": 0,
      "charge_kw": 0,
      "classification": "hold",
      "end_time": "2025-11-04T21:30:00+01:00",
      "export_kwh": 0,
      "export_price_sek_kwh": 0.06,
      "export_revenue": 0,
      "import_price_sek_kwh": 0.94,
      "is_cheap": true,
      "load_forecast_kwh": 0.29,
      "priority": "low",
      "projected_battery_cost": 0.2,
      "projected_soc_kwh": 25.21,
      "projected_soc_percent": 74.15,
      "pv_forecast_kwh": 0,
      "reason": "no_action_needed",
      "slot_number": 86,
      "soc_target_percent": 74.15,
      "start_time": "2025-11-04T21:15:00+01:00",
      "water_from_battery_kwh": 0,
      "water_from_grid_kwh": 0,
      "water_from_pv_kwh": 0,
      "water_heating_kw": 0
    },
    {
      "adjusted_load_kwh": 0.21,
      "adjusted_pv_kwh": 0,
      "battery_charge_kw": 7.8,
      "battery_discharge_kw": 0,
      "charge_kw": 8,
      "classification": "charge",
      "end_time": "2025-11-04T21:45:00+01:00",
      "export_kwh": 0,
      "export_price_sek_kwh": 0.03,
      "export_revenue": 0,
      "import_price_sek_kwh": 0.9,
      "is_cheap": true,
      "load_forecast_kwh": 0.2,
      "priority": "high",
      "projected_battery_cost": 0.25,
      "projected_soc_kwh": 27.16,
      "projected_soc_percent": 79.89,
      "pv_forecast_kwh": 0,
      "reason": "cheap_grid_power",
      "slot_number": 87,
      "soc_target_percent": 85.62,
      "start_time": "2025-11-04T21:30:00+01:00",
      "water_from_battery_kwh": 0,
      "water_from_grid_kwh": 0,
      "water_from_pv_kwh": 0,
      "water_heating_kw": 0
    },
    {
      "adjusted_load_kwh": 0.33,
      "adjusted_pv_kwh": 0,
      "battery_charge_kw": 7.8,
      "battery_discharge_kw": 0,
      "charge_kw": 8,
      "classification": "charge",
      "end_time": "2025-11-04T22:00:00+01:00",
      "export_kwh": 0,
      "export_price_sek_kwh": 0.03,
      "export_revenue": 0,
      "import_price_sek_kwh": 0.89,
      "is_cheap": true,
      "load_forecast_kwh": 0.32,
      "priority": "high",
      "projected_battery_cost": 0.3,
      "projected_soc_kwh": 29.11,
      "projected_soc_percent": 85.62,
      "pv_forecast_kwh": 0,
      "reason": "cheap_grid_power",
      "slot_number": 88,
      "soc_target_percent": 85.62,
      "start_time": "2025-11-04T21:45:00+01:00",
      "water_from_battery_kwh": 0,
      "water_from_grid_kwh": 0,
      "water_from_pv_kwh": 0,
      "water_heating_kw": 0
    },
    {
      "adjusted_load_kwh": 0.3,
      "adjusted_pv_kwh": 0,
      "battery_charge_kw": 0,
      "battery_discharge_kw": 0,
      "charge_kw": 0,
      "classification": "hold",
      "end_time": "2025-11-04T22:15:00+01:00",
      "export_kwh": 0,
      "export_price_sek_kwh": 0.02,
      "export_revenue": 0,
      "import_price_sek_kwh": 0.89,
      "is_cheap": true,
      "load_forecast_kwh": 0.29,
      "priority": "low",
      "projected_battery_cost": 0.3,
      "projected_soc_kwh": 29.11,
      "projected_soc_percent": 85.62,
      "pv_forecast_kwh": 0,
      "reason": "no_action_needed",
      "slot_number": 89,
      "soc_target_percent": 85.62,
      "start_time": "2025-11-04T22:00:00+01:00",
      "water_from_battery_kwh": 0,
      "water_from_grid_kwh": 0.75,
      "water_from_pv_kwh": 0,
      "water_heating_kw": 3
    },
    {
      "adjusted_load_kwh": 0.19,
      "adjusted_pv_kwh": 0,
      "battery_charge_kw": 0,
      "battery_discharge_kw": 0,
      "charge_kw": 0,
      "classification": "hold",
      "end_time": "2025-11-04T22:30:00+01:00",
      "export_kwh": 0,
      "export_price_sek_kwh": 0,
      "export_revenue": 0,
      "import_price_sek_kwh": 0.86,
      "is_cheap": true,
      "load_forecast_kwh": 0.18,
      "priority": "low",
      "projected_battery_cost": 0.3,
      "projected_soc_kwh": 29.11,
      "projected_soc_percent": 85.62,
      "pv_forecast_kwh": 0,
      "reason": "no_action_needed",
      "slot_number": 90,
      "soc_target_percent": 85.62,
      "start_time": "2025-11-04T22:15:00+01:00",
      "water_from_battery_kwh": 0,
      "water_from_grid_kwh": 0.75,
      "water_from_pv_kwh": 0,
      "water_heating_kw": 3
    },
    {
      "adjusted_load_kwh": 0.17,
      "adjusted_pv_kwh": 0,
      "battery_charge_kw": 0,
      "battery_discharge_kw": 0,
      "charge_kw": 0,
      "classification": "hold",
      "end_time": "2025-11-04T22:45:00+01:00",
      "export_kwh": 0,
      "export_price_sek_kwh": 0,
      "export_revenue": 0,
      "import_price_sek_kwh": 0.85,
      "is_cheap": true,
      "load_forecast_kwh": 0.16,
      "priority": "low",
      "projected_battery_cost": 0.3,
      "projected_soc_kwh": 29.11,
      "projected_soc_percent": 85.62,
      "pv_forecast_kwh": 0,
      "reason": "no_action_needed",
      "slot_number": 91,
      "soc_target_percent": 85.62,
      "start_time": "2025-11-04T22:30:00+01:00",
      "water_from_battery_kwh": 0,
      "water_from_grid_kwh": 0.75,
      "water_from_pv_kwh": 0,
      "water_heating_kw": 3
    },
    {
      "adjusted_load_kwh": 0.17,
      "adjusted_pv_kwh": 0,
      "battery_charge_kw": 0,
      "battery_discharge_kw": 0,
      "charge_kw": 0,
      "classification": "hold",
      "end_time": "2025-11-04T23:00:00+01:00",
      "export_kwh": 0,
      "export_price_sek_kwh": -0.01,
      "export_revenue": 0,
      "import_price_sek_kwh": 0.85,
      "is_cheap": true,
      "load_forecast_kwh": 0.16,
      "priority": "low",
      "projected_battery_cost": 0.3,
      "projected_soc_kwh": 29.11,
      "projected_soc_percent": 85.62,
      "pv_forecast_kwh": 0,
      "reason": "no_action_needed",
      "slot_number": 92,
      "soc_target_percent": 85.62,
      "start_time": "2025-11-04T22:45:00+01:00",
      "water_from_battery_kwh": 0,
      "water_from_grid_kwh": 0.75,
      "water_from_pv_kwh": 0,
      "water_heating_kw": 3
    },
    {
      "adjusted_load_kwh": 0.2,
      "adjusted_pv_kwh": 0,
      "battery_charge_kw": 0,
      "battery_discharge_kw": 0,
      "charge_kw": 0,
      "classification": "hold",
      "end_time": "2025-11-04T23:15:00+01:00",
      "export_kwh": 0,
      "export_price_sek_kwh": 0,
      "export_revenue": 0,
      "import_price_sek_kwh": 0.85,
      "is_cheap": true,
      "load_forecast_kwh": 0.2,
      "priority": "low",
      "projected_battery_cost": 0.3,
      "projected_soc_kwh": 29.11,
      "projected_soc_percent": 85.62,
      "pv_forecast_kwh": 0,
      "reason": "no_action_needed",
      "slot_number": 93,
      "soc_target_percent": 85.62,
      "start_time": "2025-11-04T23:00:00+01:00",
      "water_from_battery_kwh": 0,
      "water_from_grid_kwh": 0.75,
      "water_from_pv_kwh": 0,
      "water_heating_kw": 3
    },
    {
      "adjusted_load_kwh": 0.18,
      "adjusted_pv_kwh": 0,
      "battery_charge_kw": 0,
      "battery_discharge_kw": 0,
      "charge_kw": 0,
      "classification": "hold",
      "end_time": "2025-11-04T23:30:00+01:00",
      "export_kwh": 0,
      "export_price_sek_kwh": -0.01,
      "export_revenue": 0,
      "import_price_sek_kwh": 0.85,
      "is_cheap": true,
      "load_forecast_kwh": 0.17,
      "priority": "low",
      "projected_battery_cost": 0.3,
      "projected_soc_kwh": 29.11,
      "projected_soc_percent": 85.62,
      "pv_forecast_kwh": 0,
      "reason": "no_action_needed",
      "slot_number": 94,
      "soc_target_percent": 85.62,
      "start_time": "2025-11-04T23:15:00+01:00",
      "water_from_battery_kwh": 0,
      "water_from_grid_kwh": 0.75,
      "water_from_pv_kwh": 0,
      "water_heating_kw": 3
    },
    {
      "adjusted_load_kwh": 0.18,
      "adjusted_pv_kwh": 0,
      "battery_charge_kw": 0,
      "battery_discharge_kw": 0,
      "charge_kw": 0,
      "classification": "hold",
      "end_time": "2025-11-04T23:45:00+01:00",
      "export_kwh": 0,
      "export_price_sek_kwh": -0.01,
      "export_revenue": 0,
      "import_price_sek_kwh": 0.84,
      "is_cheap": true,
      "load_forecast_kwh": 0.18,
      "priority": "low",
      "projected_battery_cost": 0.3,
      "projected_soc_kwh": 29.11,
      "projected_soc_percent": 85.62,
      "pv_forecast_kwh": 0,
      "reason": "no_action_needed",
      "slot_number": 95,
      "soc_target_percent": 85.62,
      "start_time": "2025-11-04T23:30:00+01:00",
      "water_from_battery_kwh": 0,
      "water_from_grid_kwh": 0.75,
      "water_from_pv_kwh": 0,
      "water_heating_kw": 3
    },
    {
      "adjusted_load_kwh": 0.13,
      "adjusted_pv_kwh": 0,
      "battery_charge_kw": 0,
      "battery_discharge_kw": 0,
      "charge_kw": 0,
      "classification": "hold",
      "end_time": "2025-11-05T00:00:00+01:00",
      "export_kwh": 0,
      "export_price_sek_kwh": -0.02,
      "export_revenue": 0,
      "import_price_sek_kwh": 0.83,
      "is_cheap": true,
      "load_forecast_kwh": 0.12,
      "priority": "low",
      "projected_battery_cost": 0.3,
      "projected_soc_kwh": 29.11,
      "projected_soc_percent": 85.62,
      "pv_forecast_kwh": 0,
      "reason": "no_action_needed",
      "slot_number": 96,
      "soc_target_percent": 85.62,
      "start_time": "2025-11-04T23:45:00+01:00",
      "water_from_battery_kwh": 0,
      "water_from_grid_kwh": 0.75,
      "water_from_pv_kwh": 0,
      "water_heating_kw": 3
    }
  ],
  "meta": {
    "planned_at": "2025-11-04T11:36:01.603947",
    "planner_version": "v0.3.0-13-gf21d0ab-dirty"
  }
}